scmdata/__init__.py
scmdata/_base.py
scmdata/_typing.py
scmdata/_xarray.py
scmdata/data/metric_conversions.csv
scmdata/database/__init__.py
scmdata/database/_database.py
scmdata/database/_utils.py
scmdata/database/backends/__init__.py
scmdata/database/backends/base.py
scmdata/database/backends/netcdf.py
scmdata/errors.py
scmdata/filters.py
scmdata/groupby.py
scmdata/netcdf.py
scmdata/offsets.py
scmdata/ops.py
scmdata/plotting.py
scmdata/processing.py
scmdata/py.typed
scmdata/pyam_compat.py
scmdata/run.py
scmdata/testing.py
scmdata/time.py
scmdata/timeseries.py
scmdata/units.py
scmdata-0.18.0.dist-info/LICENSE
scmdata-0.18.0.dist-info/METADATA
scmdata-0.18.0.dist-info/WHEEL
scmdata-0.18.0.dist-info/RECORD
