Metadata-Version: 2.3
Name: scmdata
Version: 0.18.0
Summary: scmdata provides some useful data handling routines for dealing with data related to simple climate models (SCMs aka reduced complexity climate models, RCMs)
Keywords: data,simple climate model,climate,scm
Author: Jared Lewis
Author-email: jared.lewis@climate-resource.com
Requires-Python: >=3.9,<4
Classifier: Development Status :: 4 - Beta
Classifier: Intended Audience :: Developers
Classifier: License :: OSI Approved :: BSD License
Classifier: Operating System :: OS Independent
Classifier: Programming Language :: Python :: 3
Classifier: Programming Language :: Python :: 3.9
Classifier: Programming Language :: Python :: 3.10
Classifier: Programming Language :: Python :: 3.11
Classifier: Programming Language :: Python :: 3.12
Classifier: Programming Language :: Python :: 3.13
Classifier: Programming Language :: Python :: 3.8
Provides-Extra: notebooks
Provides-Extra: optional
Provides-Extra: plots
Requires-Dist: cftime (>=1.5)
Requires-Dist: joblib ; extra == "optional"
Requires-Dist: matplotlib (>=3.7.1) ; extra == "plots"
Requires-Dist: nc-time-axis (>=1.2.0) ; extra == "plots"
Requires-Dist: netCDF4 ; extra == "optional"
Requires-Dist: notebook (>=7) ; extra == "notebooks"
Requires-Dist: numpy
Requires-Dist: openpyxl ; extra == "optional"
Requires-Dist: openscm-units
Requires-Dist: packaging
Requires-Dist: pandas (>=1.1)
Requires-Dist: pint
Requires-Dist: pint-pandas
Requires-Dist: pyam-iamc ; extra == "optional"
Requires-Dist: python-dateutil
Requires-Dist: scipy ; extra == "optional"
Requires-Dist: seaborn (>=0.12.0) ; extra == "plots"
Requires-Dist: six
Requires-Dist: tqdm
Requires-Dist: typing-extensions
Requires-Dist: xarray (<=2025.03) ; python_version == "3.9"
Requires-Dist: xarray ; python_version >= "3.10"
Requires-Dist: xlrd ; extra == "optional"
